minecraft_get_building/get_building_data.py
minecraft_get_building-0.1.3.dist-info/entry_points.txt
minecraft_get_building-0.1.3.dist-info/LICENSE
minecraft_get_building-0.1.3.dist-info/WHEEL
minecraft_get_building-0.1.3.dist-info/METADATA
minecraft_get_building-0.1.3.dist-info/RECORD
